PyConnectTelnet/__init__.py
PyConnectTelnet/connect_telnet.py
PyConnectTelnet-0.1.dist-info/METADATA
PyConnectTelnet-0.1.dist-info/WHEEL
PyConnectTelnet-0.1.dist-info/top_level.txt
PyConnectTelnet-0.1.dist-info/RECORD
