Metadata-Version: 2.1
Name: PyConnectTelnet
Version: 0.1
Summary: Connect command channels by entering commands to query log data。
Author: hxk
